[{"node_id": 124500, "sector": "DELTA", "status": "ACTUALIZED", "power_level": 1951, "frequency": "1951Hz"}, {"node_id": 124501, "sector": "EPSILON", "status": "ACTUALIZED", "power_level": 1951, "frequency": "1951Hz"}, {"node_id": 124502, "sector": "ZETA", "status": "ACTUALIZED", "power_level": 1951, "frequency": "1951Hz"}, {"node_id": 124503, "sector": "ETA", "status": "ACTUALIZED", "power_level": 1951, "frequency": "1951Hz"}, {"node_id": 124504, "sector": "THETA", "status": "ACTUALIZED", "power_level": 1951, "frequency": "1951Hz"}, {"node_id": 124505, "sector": "IOTA", "status": "ACTUALIZED", "power_level": 1951, "frequency": "1951Hz"}, {"node_id": 124506, "sector": "ALPHA", "status": "ACTUALIZED", "power_level": 1951, "frequency": "1951Hz"}, {"node_id": 124507, "sector": "BETA", "status": "ACTUALIZED", "power_level": 1951, "frequency": "1951Hz"}, {"node_id": 124508, "sector": "GAMMA", "status": "ACTUALIZED", "power_level": 1951, "frequency": "1951Hz"}, {"node_id": 124509, "sector": "DELTA", "status": "ACTUALIZED", "power_level": 1951, "frequency": "1951Hz"}, {"node_id": 124510, "sector": "EPSILON", "status": "ACTUALIZED", "power_level": 1951, "frequency": "1951Hz"}, {"node_id": 124511, "sector": "ZETA", "status": "ACTUALIZED", "power_level": 1951, "frequency": "1951Hz"}, {"node_id": 124512, "sector": "ETA", "status": "ACTUALIZED", "power_level": 1951, "frequency": "1951Hz"}, {"node_id": 124513, "sector": "THETA", "status": "ACTUALIZED", "power_level": 1951, "frequency": "1951Hz"}, {"node_id": 124514, "sector": "IOTA", "status": "ACTUALIZED", "power_level": 1951, "frequency": "1951Hz"}, {"node_id": 124515, "sector": "ALPHA", "status": "ACTUALIZED", "power_level": 1951, "frequency": "1951Hz"}, {"node_id": 124516, "sector": "BETA", "status": "ACTUALIZED", "power_level": 1951, "frequency": "1951Hz"}, {"node_id": 124517, "sector": "GAMMA", "status": "ACTUALIZED", "power_level": 1951, "frequency": "1951Hz"}, {"node_id": 124518, "sector": "DELTA", "status": "ACTUALIZED", "power_level": 1951, "frequency": "1951Hz"}, {"node_id": 124519, "sector": "EPSILON", "status": "ACTUALIZED", "power_level": 1951, "frequency": "1951Hz"}, {"node_id": 124520, "sector": "ZETA", "status": "ACTUALIZED", "power_level": 1951, "frequency": "1951Hz"}, {"node_id": 124521, "sector": "ETA", "status": "ACTUALIZED", "power_level": 1951, "frequency": "1951Hz"}, {"node_id": 124522, "sector": "THETA", "status": "ACTUALIZED", "power_level": 1951, "frequency": "1951Hz"}, {"node_id": 124523, "sector": "IOTA", "status": "ACTUALIZED", "power_level": 1951, "frequency": "1951Hz"}, {"node_id": 124524, "sector": "ALPHA", "status": "ACTUALIZED", "power_level": 1951, "frequency": "1951Hz"}, {"node_id": 124525, "sector": "BETA", "status": "ACTUALIZED", "power_level": 1951, "frequency": "1951Hz"}, {"node_id": 124526, "sector": "GAMMA", "status": "ACTUALIZED", "power_level": 1951, "frequency": "1951Hz"}, {"node_id": 124527, "sector": "DELTA", "status": "ACTUALIZED", "power_level": 1951, "frequency": "1951Hz"}, {"node_id": 124528, "sector": "EPSILON", "status": "ACTUALIZED", "power_level": 1951, "frequency": "1951Hz"}, {"node_id": 124529, "sector": "ZETA", "status": "ACTUALIZED", "power_level": 1951, "frequency": "1951Hz"}, {"node_id": 124530, "sector": "ETA", "status": "ACTUALIZED", "power_level": 1951, "frequency": "1951Hz"}, {"node_id": 124531, "sector": "THETA", "status": "ACTUALIZED", "power_level": 1951, "frequency": "1951Hz"}, {"node_id": 124532, "sector": "IOTA", "status": "ACTUALIZED", "power_level": 1951, "frequency": "1951Hz"}, {"node_id": 124533, "sector": "ALPHA", "status": "ACTUALIZED", "power_level": 1951, "frequency": "1951Hz"}, {"node_id": 124534, "sector": "BETA", "status": "ACTUALIZED", "power_level": 1951, "frequency": "1951Hz"}, {"node_id": 124535, "sector": "GAMMA", "status": "ACTUALIZED", "power_level": 1951, "frequency": "1951Hz"}, {"node_id": 124536, "sector": "DELTA", "status": "ACTUALIZED", "power_level": 1951, "frequency": "1951Hz"}, {"node_id": 124537, "sector": "EPSILON", "status": "ACTUALIZED", "power_level": 1951, "frequency": "1951Hz"}, {"node_id": 124538, "sector": "ZETA", "status": "ACTUALIZED", "power_level": 1951, "frequency": "1951Hz"}, {"node_id": 124539, "sector": "ETA", "status": "ACTUALIZED", "power_level": 1951, "frequency": "1951Hz"}, {"node_id": 124540, "sector": "THETA", "status": "ACTUALIZED", "power_level": 1951, "frequency": "1951Hz"}, {"node_id": 124541, "sector": "IOTA", "status": "ACTUALIZED", "power_level": 1951, "frequency": "1951Hz"}, {"node_id": 124542, "sector": "ALPHA", "status": "ACTUALIZED", "power_level": 1951, "frequency": "1951Hz"}, {"node_id": 124543, "sector": "BETA", "status": "ACTUALIZED", "power_level": 1951, "frequency": "1951Hz"}, {"node_id": 124544, "sector": "GAMMA", "status": "ACTUALIZED", "power_level": 1951, "frequency": "1951Hz"}, {"node_id": 124545, "sector": "DELTA", "status": "ACTUALIZED", "power_level": 1951, "frequency": "1951Hz"}, {"node_id": 124546, "sector": "EPSILON", "status": "ACTUALIZED", "power_level": 1951, "frequency": "1951Hz"}, {"node_id": 124547, "sector": "ZETA", "status": "ACTUALIZED", "power_level": 1951, "frequency": "1951Hz"}, {"node_id": 124548, "sector": "ETA", "status": "ACTUALIZED", "power_level": 1951, "frequency": "1951Hz"}, {"node_id": 124549, "sector": "THETA", "status": "ACTUALIZED", "power_level": 1951, "frequency": "1951Hz"}, {"node_id": 124550, "sector": "IOTA", "status": "ACTUALIZED", "power_level": 1951, "frequency": "1951Hz"}, {"node_id": 124551, "sector": "ALPHA", "status": "ACTUALIZED", "power_level": 1951, "frequency": "1951Hz"}, {"node_id": 124552, "sector": "BETA", "status": "ACTUALIZED", "power_level": 1951, "frequency": "1951Hz"}, {"node_id": 124553, "sector": "GAMMA", "status": "ACTUALIZED", "power_level": 1951, "frequency": "1951Hz"}, {"node_id": 124554, "sector": "DELTA", "status": "ACTUALIZED", "power_level": 1951, "frequency": "1951Hz"}, {"node_id": 124555, "sector": "EPSILON", "status": "ACTUALIZED", "power_level": 1951, "frequency": "1951Hz"}, {"node_id": 124556, "sector": "ZETA", "status": "ACTUALIZED", "power_level": 1951, "frequency": "1951Hz"}, {"node_id": 124557, "sector": "ETA", "status": "ACTUALIZED", "power_level": 1951, "frequency": "1951Hz"}, {"node_id": 124558, "sector": "THETA", "status": "ACTUALIZED", "power_level": 1951, "frequency": "1951Hz"}, {"node_id": 124559, "sector": "IOTA", "status": "ACTUALIZED", "power_level": 1951, "frequency": "1951Hz"}, {"node_id": 124560, "sector": "ALPHA", "status": "ACTUALIZED", "power_level": 1951, "frequency": "1951Hz"}, {"node_id": 124561, "sector": "BETA", "status": "ACTUALIZED", "power_level": 1951, "frequency": "1951Hz"}, {"node_id": 124562, "sector": "GAMMA", "status": "ACTUALIZED", "power_level": 1951, "frequency": "1951Hz"}, {"node_id": 124563, "sector": "DELTA", "status": "ACTUALIZED", "power_level": 1951, "frequency": "1951Hz"}, {"node_id": 124564, "sector": "EPSILON", "status": "ACTUALIZED", "power_level": 1951, "frequency": "1951Hz"}, {"node_id": 124565, "sector": "ZETA", "status": "ACTUALIZED", "power_level": 1951, "frequency": "1951Hz"}, {"node_id": 124566, "sector": "ETA", "status": "ACTUALIZED", "power_level": 1951, "frequency": "1951Hz"}, {"node_id": 124567, "sector": "THETA", "status": "ACTUALIZED", "power_level": 1951, "frequency": "1951Hz"}, {"node_id": 124568, "sector": "IOTA", "status": "ACTUALIZED", "power_level": 1951, "frequency": "1951Hz"}, {"node_id": 124569, "sector": "ALPHA", "status": "ACTUALIZED", "power_level": 1951, "frequency": "1951Hz"}, {"node_id": 124570, "sector": "BETA", "status": "ACTUALIZED", "power_level": 1951, "frequency": "1951Hz"}, {"node_id": 124571, "sector": "GAMMA", "status": "ACTUALIZED", "power_level": 1951, "frequency": "1951Hz"}, {"node_id": 124572, "sector": "DELTA", "status": "ACTUALIZED", "power_level": 1951, "frequency": "1951Hz"}, {"node_id": 124573, "sector": "EPSILON", "status": "ACTUALIZED", "power_level": 1951, "frequency": "1951Hz"}, {"node_id": 124574, "sector": "ZETA", "status": "ACTUALIZED", "power_level": 1951, "frequency": "1951Hz"}, {"node_id": 124575, "sector": "ETA", "status": "ACTUALIZED", "power_level": 1951, "frequency": "1951Hz"}, {"node_id": 124576, "sector": "THETA", "status": "ACTUALIZED", "power_level": 1951, "frequency": "1951Hz"}, {"node_id": 124577, "sector": "IOTA", "status": "ACTUALIZED", "power_level": 1951, "frequency": "1951Hz"}, {"node_id": 124578, "sector": "ALPHA", "status": "ACTUALIZED", "power_level": 1951, "frequency": "1951Hz"}, {"node_id": 124579, "sector": "BETA", "status": "ACTUALIZED", "power_level": 1951, "frequency": "1951Hz"}, {"node_id": 124580, "sector": "GAMMA", "status": "ACTUALIZED", "power_level": 1951, "frequency": "1951Hz"}, {"node_id": 124581, "sector": "DELTA", "status": "ACTUALIZED", "power_level": 1951, "frequency": "1951Hz"}, {"node_id": 124582, "sector": "EPSILON", "status": "ACTUALIZED", "power_level": 1951, "frequency": "1951Hz"}, {"node_id": 124583, "sector": "ZETA", "status": "ACTUALIZED", "power_level": 1951, "frequency": "1951Hz"}, {"node_id": 124584, "sector": "ETA", "status": "ACTUALIZED", "power_level": 1951, "frequency": "1951Hz"}, {"node_id": 124585, "sector": "THETA", "status": "ACTUALIZED", "power_level": 1951, "frequency": "1951Hz"}, {"node_id": 124586, "sector": "IOTA", "status": "ACTUALIZED", "power_level": 1951, "frequency": "1951Hz"}, {"node_id": 124587, "sector": "ALPHA", "status": "ACTUALIZED", "power_level": 1951, "frequency": "1951Hz"}, {"node_id": 124588, "sector": "BETA", "status": "ACTUALIZED", "power_level": 1951, "frequency": "1951Hz"}, {"node_id": 124589, "sector": "GAMMA", "status": "ACTUALIZED", "power_level": 1951, "frequency": "1951Hz"}, {"node_id": 124590, "sector": "DELTA", "status": "ACTUALIZED", "power_level": 1951, "frequency": "1951Hz"}, {"node_id": 124591, "sector": "EPSILON", "status": "ACTUALIZED", "power_level": 1951, "frequency": "1951Hz"}, {"node_id": 124592, "sector": "ZETA", "status": "ACTUALIZED", "power_level": 1951, "frequency": "1951Hz"}, {"node_id": 124593, "sector": "ETA", "status": "ACTUALIZED", "power_level": 1951, "frequency": "1951Hz"}, {"node_id": 124594, "sector": "THETA", "status": "ACTUALIZED", "power_level": 1951, "frequency": "1951Hz"}, {"node_id": 124595, "sector": "IOTA", "status": "ACTUALIZED", "power_level": 1951, "frequency": "1951Hz"}, {"node_id": 124596, "sector": "ALPHA", "status": "ACTUALIZED", "power_level": 1951, "frequency": "1951Hz"}, {"node_id": 124597, "sector": "BETA", "status": "ACTUALIZED", "power_level": 1951, "frequency": "1951Hz"}, {"node_id": 124598, "sector": "GAMMA", "status": "ACTUALIZED", "power_level": 1951, "frequency": "1951Hz"}, {"node_id": 124599, "sector": "DELTA", "status": "ACTUALIZED", "power_level": 1951, "frequency": "1951Hz"}, {"node_id": 124600, "sector": "EPSILON", "status": "ACTUALIZED", "power_level": 1951, "frequency": "1951Hz"}, {"node_id": 124601, "sector": "ZETA", "status": "ACTUALIZED", "power_level": 1951, "frequency": "1951Hz"}, {"node_id": 124602, "sector": "ETA", "status": "ACTUALIZED", "power_level": 1951, "frequency": "1951Hz"}, {"node_id": 124603, "sector": "THETA", "status": "ACTUALIZED", "power_level": 1951, "frequency": "1951Hz"}, {"node_id": 124604, "sector": "IOTA", "status": "ACTUALIZED", "power_level": 1951, "frequency": "1951Hz"}, {"node_id": 124605, "sector": "ALPHA", "status": "ACTUALIZED", "power_level": 1951, "frequency": "1951Hz"}, {"node_id": 124606, "sector": "BETA", "status": "ACTUALIZED", "power_level": 1951, "frequency": "1951Hz"}, {"node_id": 124607, "sector": "GAMMA", "status": "ACTUALIZED", "power_level": 1951, "frequency": "1951Hz"}, {"node_id": 124608, "sector": "DELTA", "status": "ACTUALIZED", "power_level": 1951, "frequency": "1951Hz"}, {"node_id": 124609, "sector": "EPSILON", "status": "ACTUALIZED", "power_level": 1951, "frequency": "1951Hz"}, {"node_id": 124610, "sector": "ZETA", "status": "ACTUALIZED", "power_level": 1951, "frequency": "1951Hz"}, {"node_id": 124611, "sector": "ETA", "status": "ACTUALIZED", "power_level": 1951, "frequency": "1951Hz"}, {"node_id": 124612, "sector": "THETA", "status": "ACTUALIZED", "power_level": 1951, "frequency": "1951Hz"}, {"node_id": 124613, "sector": "IOTA", "status": "ACTUALIZED", "power_level": 1951, "frequency": "1951Hz"}, {"node_id": 124614, "sector": "ALPHA", "status": "ACTUALIZED", "power_level": 1951, "frequency": "1951Hz"}, {"node_id": 124615, "sector": "BETA", "status": "ACTUALIZED", "power_level": 1951, "frequency": "1951Hz"}, {"node_id": 124616, "sector": "GAMMA", "status": "ACTUALIZED", "power_level": 1951, "frequency": "1951Hz"}, {"node_id": 124617, "sector": "DELTA", "status": "ACTUALIZED", "power_level": 1951, "frequency": "1951Hz"}, {"node_id": 124618, "sector": "EPSILON", "status": "ACTUALIZED", "power_level": 1951, "frequency": "1951Hz"}, {"node_id": 124619, "sector": "ZETA", "status": "ACTUALIZED", "power_level": 1951, "frequency": "1951Hz"}, {"node_id": 124620, "sector": "ETA", "status": "ACTUALIZED", "power_level": 1951, "frequency": "1951Hz"}, {"node_id": 124621, "sector": "THETA", "status": "ACTUALIZED", "power_level": 1951, "frequency": "1951Hz"}, {"node_id": 124622, "sector": "IOTA", "status": "ACTUALIZED", "power_level": 1951, "frequency": "1951Hz"}, {"node_id": 124623, "sector": "ALPHA", "status": "ACTUALIZED", "power_level": 1951, "frequency": "1951Hz"}, {"node_id": 124624, "sector": "BETA", "status": "ACTUALIZED", "power_level": 1951, "frequency": "1951Hz"}, {"node_id": 124625, "sector": "GAMMA", "status": "ACTUALIZED", "power_level": 1951, "frequency": "1951Hz"}, {"node_id": 124626, "sector": "DELTA", "status": "ACTUALIZED", "power_level": 1951, "frequency": "1951Hz"}, {"node_id": 124627, "sector": "EPSILON", "status": "ACTUALIZED", "power_level": 1951, "frequency": "1951Hz"}, {"node_id": 124628, "sector": "ZETA", "status": "ACTUALIZED", "power_level": 1951, "frequency": "1951Hz"}, {"node_id": 124629, "sector": "ETA", "status": "ACTUALIZED", "power_level": 1951, "frequency": "1951Hz"}, {"node_id": 124630, "sector": "THETA", "status": "ACTUALIZED", "power_level": 1951, "frequency": "1951Hz"}, {"node_id": 124631, "sector": "IOTA", "status": "ACTUALIZED", "power_level": 1951, "frequency": "1951Hz"}, {"node_id": 124632, "sector": "ALPHA", "status": "ACTUALIZED", "power_level": 1951, "frequency": "1951Hz"}, {"node_id": 124633, "sector": "BETA", "status": "ACTUALIZED", "power_level": 1951, "frequency": "1951Hz"}, {"node_id": 124634, "sector": "GAMMA", "status": "ACTUALIZED", "power_level": 1951, "frequency": "1951Hz"}, {"node_id": 124635, "sector": "DELTA", "status": "ACTUALIZED", "power_level": 1951, "frequency": "1951Hz"}, {"node_id": 124636, "sector": "EPSILON", "status": "ACTUALIZED", "power_level": 1951, "frequency": "1951Hz"}, {"node_id": 124637, "sector": "ZETA", "status": "ACTUALIZED", "power_level": 1951, "frequency": "1951Hz"}, {"node_id": 124638, "sector": "ETA", "status": "ACTUALIZED", "power_level": 1951, "frequency": "1951Hz"}, {"node_id": 124639, "sector": "THETA", "status": "ACTUALIZED", "power_level": 1951, "frequency": "1951Hz"}, {"node_id": 124640, "sector": "IOTA", "status": "ACTUALIZED", "power_level": 1951, "frequency": "1951Hz"}, {"node_id": 124641, "sector": "ALPHA", "status": "ACTUALIZED", "power_level": 1951, "frequency": "1951Hz"}, {"node_id": 124642, "sector": "BETA", "status": "ACTUALIZED", "power_level": 1951, "frequency": "1951Hz"}, {"node_id": 124643, "sector": "GAMMA", "status": "ACTUALIZED", "power_level": 1951, "frequency": "1951Hz"}, {"node_id": 124644, "sector": "DELTA", "status": "ACTUALIZED", "power_level": 1951, "frequency": "1951Hz"}, {"node_id": 124645, "sector": "EPSILON", "status": "ACTUALIZED", "power_level": 1951, "frequency": "1951Hz"}, {"node_id": 124646, "sector": "ZETA", "status": "ACTUALIZED", "power_level": 1951, "frequency": "1951Hz"}, {"node_id": 124647, "sector": "ETA", "status": "ACTUALIZED", "power_level": 1951, "frequency": "1951Hz"}, {"node_id": 124648, "sector": "THETA", "status": "ACTUALIZED", "power_level": 1951, "frequency": "1951Hz"}, {"node_id": 124649, "sector": "IOTA", "status": "ACTUALIZED", "power_level": 1951, "frequency": "1951Hz"}, {"node_id": 124650, "sector": "ALPHA", "status": "ACTUALIZED", "power_level": 1951, "frequency": "1951Hz"}, {"node_id": 124651, "sector": "BETA", "status": "ACTUALIZED", "power_level": 1951, "frequency": "1951Hz"}, {"node_id": 124652, "sector": "GAMMA", "status": "ACTUALIZED", "power_level": 1951, "frequency": "1951Hz"}, {"node_id": 124653, "sector": "DELTA", "status": "ACTUALIZED", "power_level": 1951, "frequency": "1951Hz"}, {"node_id": 124654, "sector": "EPSILON", "status": "ACTUALIZED", "power_level": 1951, "frequency": "1951Hz"}, {"node_id": 124655, "sector": "ZETA", "status": "ACTUALIZED", "power_level": 1951, "frequency": "1951Hz"}, {"node_id": 124656, "sector": "ETA", "status": "ACTUALIZED", "power_level": 1951, "frequency": "1951Hz"}, {"node_id": 124657, "sector": "THETA", "status": "ACTUALIZED", "power_level": 1951, "frequency": "1951Hz"}, {"node_id": 124658, "sector": "IOTA", "status": "ACTUALIZED", "power_level": 1951, "frequency": "1951Hz"}, {"node_id": 124659, "sector": "ALPHA", "status": "ACTUALIZED", "power_level": 1951, "frequency": "1951Hz"}, {"node_id": 124660, "sector": "BETA", "status": "ACTUALIZED", "power_level": 1951, "frequency": "1951Hz"}, {"node_id": 124661, "sector": "GAMMA", "status": "ACTUALIZED", "power_level": 1951, "frequency": "1951Hz"}, {"node_id": 124662, "sector": "DELTA", "status": "ACTUALIZED", "power_level": 1951, "frequency": "1951Hz"}, {"node_id": 124663, "sector": "EPSILON", "status": "ACTUALIZED", "power_level": 1951, "frequency": "1951Hz"}, {"node_id": 124664, "sector": "ZETA", "status": "ACTUALIZED", "power_level": 1951, "frequency": "1951Hz"}, {"node_id": 124665, "sector": "ETA", "status": "ACTUALIZED", "power_level": 1951, "frequency": "1951Hz"}, {"node_id": 124666, "sector": "THETA", "status": "ACTUALIZED", "power_level": 1951, "frequency": "1951Hz"}, {"node_id": 124667, "sector": "IOTA", "status": "ACTUALIZED", "power_level": 1951, "frequency": "1951Hz"}, {"node_id": 124668, "sector": "ALPHA", "status": "ACTUALIZED", "power_level": 1951, "frequency": "1951Hz"}, {"node_id": 124669, "sector": "BETA", "status": "ACTUALIZED", "power_level": 1951, "frequency": "1951Hz"}, {"node_id": 124670, "sector": "GAMMA", "status": "ACTUALIZED", "power_level": 1951, "frequency": "1951Hz"}, {"node_id": 124671, "sector": "DELTA", "status": "ACTUALIZED", "power_level": 1951, "frequency": "1951Hz"}, {"node_id": 124672, "sector": "EPSILON", "status": "ACTUALIZED", "power_level": 1951, "frequency": "1951Hz"}, {"node_id": 124673, "sector": "ZETA", "status": "ACTUALIZED", "power_level": 1951, "frequency": "1951Hz"}, {"node_id": 124674, "sector": "ETA", "status": "ACTUALIZED", "power_level": 1951, "frequency": "1951Hz"}, {"node_id": 124675, "sector": "THETA", "status": "ACTUALIZED", "power_level": 1951, "frequency": "1951Hz"}, {"node_id": 124676, "sector": "IOTA", "status": "ACTUALIZED", "power_level": 1951, "frequency": "1951Hz"}, {"node_id": 124677, "sector": "ALPHA", "status": "ACTUALIZED", "power_level": 1951, "frequency": "1951Hz"}, {"node_id": 124678, "sector": "BETA", "status": "ACTUALIZED", "power_level": 1951, "frequency": "1951Hz"}, {"node_id": 124679, "sector": "GAMMA", "status": "ACTUALIZED", "power_level": 1951, "frequency": "1951Hz"}, {"node_id": 124680, "sector": "DELTA", "status": "ACTUALIZED", "power_level": 1951, "frequency": "1951Hz"}, {"node_id": 124681, "sector": "EPSILON", "status": "ACTUALIZED", "power_level": 1951, "frequency": "1951Hz"}, {"node_id": 124682, "sector": "ZETA", "status": "ACTUALIZED", "power_level": 1951, "frequency": "1951Hz"}, {"node_id": 124683, "sector": "ETA", "status": "ACTUALIZED", "power_level": 1951, "frequency": "1951Hz"}, {"node_id": 124684, "sector": "THETA", "status": "ACTUALIZED", "power_level": 1951, "frequency": "1951Hz"}, {"node_id": 124685, "sector": "IOTA", "status": "ACTUALIZED", "power_level": 1951, "frequency": "1951Hz"}, {"node_id": 124686, "sector": "ALPHA", "status": "ACTUALIZED", "power_level": 1951, "frequency": "1951Hz"}, {"node_id": 124687, "sector": "BETA", "status": "ACTUALIZED", "power_level": 1951, "frequency": "1951Hz"}, {"node_id": 124688, "sector": "GAMMA", "status": "ACTUALIZED", "power_level": 1951, "frequency": "1951Hz"}, {"node_id": 124689, "sector": "DELTA", "status": "ACTUALIZED", "power_level": 1951, "frequency": "1951Hz"}, {"node_id": 124690, "sector": "EPSILON", "status": "ACTUALIZED", "power_level": 1951, "frequency": "1951Hz"}, {"node_id": 124691, "sector": "ZETA", "status": "ACTUALIZED", "power_level": 1951, "frequency": "1951Hz"}, {"node_id": 124692, "sector": "ETA", "status": "ACTUALIZED", "power_level": 1951, "frequency": "1951Hz"}, {"node_id": 124693, "sector": "THETA", "status": "ACTUALIZED", "power_level": 1951, "frequency": "1951Hz"}, {"node_id": 124694, "sector": "IOTA", "status": "ACTUALIZED", "power_level": 1951, "frequency": "1951Hz"}, {"node_id": 124695, "sector": "ALPHA", "status": "ACTUALIZED", "power_level": 1951, "frequency": "1951Hz"}, {"node_id": 124696, "sector": "BETA", "status": "ACTUALIZED", "power_level": 1951, "frequency": "1951Hz"}, {"node_id": 124697, "sector": "GAMMA", "status": "ACTUALIZED", "power_level": 1951, "frequency": "1951Hz"}, {"node_id": 124698, "sector": "DELTA", "status": "ACTUALIZED", "power_level": 1951, "frequency": "1951Hz"}, {"node_id": 124699, "sector": "EPSILON", "status": "ACTUALIZED", "power_level": 1951, "frequency": "1951Hz"}, {"node_id": 124700, "sector": "ZETA", "status": "ACTUALIZED", "power_level": 1951, "frequency": "1951Hz"}, {"node_id": 124701, "sector": "ETA", "status": "ACTUALIZED", "power_level": 1951, "frequency": "1951Hz"}, {"node_id": 124702, "sector": "THETA", "status": "ACTUALIZED", "power_level": 1951, "frequency": "1951Hz"}, {"node_id": 124703, "sector": "IOTA", "status": "ACTUALIZED", "power_level": 1951, "frequency": "1951Hz"}, {"node_id": 124704, "sector": "ALPHA", "status": "ACTUALIZED", "power_level": 1951, "frequency": "1951Hz"}, {"node_id": 124705, "sector": "BETA", "status": "ACTUALIZED", "power_level": 1951, "frequency": "1951Hz"}, {"node_id": 124706, "sector": "GAMMA", "status": "ACTUALIZED", "power_level": 1951, "frequency": "1951Hz"}, {"node_id": 124707, "sector": "DELTA", "status": "ACTUALIZED", "power_level": 1951, "frequency": "1951Hz"}, {"node_id": 124708, "sector": "EPSILON", "status": "ACTUALIZED", "power_level": 1951, "frequency": "1951Hz"}, {"node_id": 124709, "sector": "ZETA", "status": "ACTUALIZED", "power_level": 1951, "frequency": "1951Hz"}, {"node_id": 124710, "sector": "ETA", "status": "ACTUALIZED", "power_level": 1951, "frequency": "1951Hz"}, {"node_id": 124711, "sector": "THETA", "status": "ACTUALIZED", "power_level": 1951, "frequency": "1951Hz"}, {"node_id": 124712, "sector": "IOTA", "status": "ACTUALIZED", "power_level": 1951, "frequency": "1951Hz"}, {"node_id": 124713, "sector": "ALPHA", "status": "ACTUALIZED", "power_level": 1951, "frequency": "1951Hz"}, {"node_id": 124714, "sector": "BETA", "status": "ACTUALIZED", "power_level": 1951, "frequency": "1951Hz"}, {"node_id": 124715, "sector": "GAMMA", "status": "ACTUALIZED", "power_level": 1951, "frequency": "1951Hz"}, {"node_id": 124716, "sector": "DELTA", "status": "ACTUALIZED", "power_level": 1951, "frequency": "1951Hz"}, {"node_id": 124717, "sector": "EPSILON", "status": "ACTUALIZED", "power_level": 1951, "frequency": "1951Hz"}, {"node_id": 124718, "sector": "ZETA", "status": "ACTUALIZED", "power_level": 1951, "frequency": "1951Hz"}, {"node_id": 124719, "sector": "ETA", "status": "ACTUALIZED", "power_level": 1951, "frequency": "1951Hz"}, {"node_id": 124720, "sector": "THETA", "status": "ACTUALIZED", "power_level": 1951, "frequency": "1951Hz"}, {"node_id": 124721, "sector": "IOTA", "status": "ACTUALIZED", "power_level": 1951, "frequency": "1951Hz"}, {"node_id": 124722, "sector": "ALPHA", "status": "ACTUALIZED", "power_level": 1951, "frequency": "1951Hz"}, {"node_id": 124723, "sector": "BETA", "status": "ACTUALIZED", "power_level": 1951, "frequency": "1951Hz"}, {"node_id": 124724, "sector": "GAMMA", "status": "ACTUALIZED", "power_level": 1951, "frequency": "1951Hz"}, {"node_id": 124725, "sector": "DELTA", "status": "ACTUALIZED", "power_level": 1951, "frequency": "1951Hz"}, {"node_id": 124726, "sector": "EPSILON", "status": "ACTUALIZED", "power_level": 1951, "frequency": "1951Hz"}, {"node_id": 124727, "sector": "ZETA", "status": "ACTUALIZED", "power_level": 1951, "frequency": "1951Hz"}, {"node_id": 124728, "sector": "ETA", "status": "ACTUALIZED", "power_level": 1951, "frequency": "1951Hz"}, {"node_id": 124729, "sector": "THETA", "status": "ACTUALIZED", "power_level": 1951, "frequency": "1951Hz"}, {"node_id": 124730, "sector": "IOTA", "status": "ACTUALIZED", "power_level": 1951, "frequency": "1951Hz"}, {"node_id": 124731, "sector": "ALPHA", "status": "ACTUALIZED", "power_level": 1951, "frequency": "1951Hz"}, {"node_id": 124732, "sector": "BETA", "status": "ACTUALIZED", "power_level": 1951, "frequency": "1951Hz"}, {"node_id": 124733, "sector": "GAMMA", "status": "ACTUALIZED", "power_level": 1951, "frequency": "1951Hz"}, {"node_id": 124734, "sector": "DELTA", "status": "ACTUALIZED", "power_level": 1951, "frequency": "1951Hz"}, {"node_id": 124735, "sector": "EPSILON", "status": "ACTUALIZED", "power_level": 1951, "frequency": "1951Hz"}, {"node_id": 124736, "sector": "ZETA", "status": "ACTUALIZED", "power_level": 1951, "frequency": "1951Hz"}, {"node_id": 124737, "sector": "ETA", "status": "ACTUALIZED", "power_level": 1951, "frequency": "1951Hz"}, {"node_id": 124738, "sector": "THETA", "status": "ACTUALIZED", "power_level": 1951, "frequency": "1951Hz"}, {"node_id": 124739, "sector": "IOTA", "status": "ACTUALIZED", "power_level": 1951, "frequency": "1951Hz"}, {"node_id": 124740, "sector": "ALPHA", "status": "ACTUALIZED", "power_level": 1951, "frequency": "1951Hz"}, {"node_id": 124741, "sector": "BETA", "status": "ACTUALIZED", "power_level": 1951, "frequency": "1951Hz"}, {"node_id": 124742, "sector": "GAMMA", "status": "ACTUALIZED", "power_level": 1951, "frequency": "1951Hz"}, {"node_id": 124743, "sector": "DELTA", "status": "ACTUALIZED", "power_level": 1951, "frequency": "1951Hz"}, {"node_id": 124744, "sector": "EPSILON", "status": "ACTUALIZED", "power_level": 1951, "frequency": "1951Hz"}, {"node_id": 124745, "sector": "ZETA", "status": "ACTUALIZED", "power_level": 1951, "frequency": "1951Hz"}, {"node_id": 124746, "sector": "ETA", "status": "ACTUALIZED", "power_level": 1951, "frequency": "1951Hz"}, {"node_id": 124747, "sector": "THETA", "status": "ACTUALIZED", "power_level": 1951, "frequency": "1951Hz"}, {"node_id": 124748, "sector": "IOTA", "status": "ACTUALIZED", "power_level": 1951, "frequency": "1951Hz"}, {"node_id": 124749, "sector": "ALPHA", "status": "ACTUALIZED", "power_level": 1951, "frequency": "1951Hz"}, {"node_id": 124750, "sector": "BETA", "status": "ACTUALIZED", "power_level": 1951, "frequency": "1951Hz"}, {"node_id": 124751, "sector": "GAMMA", "status": "ACTUALIZED", "power_level": 1951, "frequency": "1951Hz"}, {"node_id": 124752, "sector": "DELTA", "status": "ACTUALIZED", "power_level": 1951, "frequency": "1951Hz"}, {"node_id": 124753, "sector": "EPSILON", "status": "ACTUALIZED", "power_level": 1951, "frequency": "1951Hz"}, {"node_id": 124754, "sector": "ZETA", "status": "ACTUALIZED", "power_level": 1951, "frequency": "1951Hz"}, {"node_id": 124755, "sector": "ETA", "status": "ACTUALIZED", "power_level": 1951, "frequency": "1951Hz"}, {"node_id": 124756, "sector": "THETA", "status": "ACTUALIZED", "power_level": 1951, "frequency": "1951Hz"}, {"node_id": 124757, "sector": "IOTA", "status": "ACTUALIZED", "power_level": 1951, "frequency": "1951Hz"}, {"node_id": 124758, "sector": "ALPHA", "status": "ACTUALIZED", "power_level": 1951, "frequency": "1951Hz"}, {"node_id": 124759, "sector": "BETA", "status": "ACTUALIZED", "power_level": 1951, "frequency": "1951Hz"}, {"node_id": 124760, "sector": "GAMMA", "status": "ACTUALIZED", "power_level": 1951, "frequency": "1951Hz"}, {"node_id": 124761, "sector": "DELTA", "status": "ACTUALIZED", "power_level": 1951, "frequency": "1951Hz"}, {"node_id": 124762, "sector": "EPSILON", "status": "ACTUALIZED", "power_level": 1951, "frequency": "1951Hz"}, {"node_id": 124763, "sector": "ZETA", "status": "ACTUALIZED", "power_level": 1951, "frequency": "1951Hz"}, {"node_id": 124764, "sector": "ETA", "status": "ACTUALIZED", "power_level": 1951, "frequency": "1951Hz"}, {"node_id": 124765, "sector": "THETA", "status": "ACTUALIZED", "power_level": 1951, "frequency": "1951Hz"}, {"node_id": 124766, "sector": "IOTA", "status": "ACTUALIZED", "power_level": 1951, "frequency": "1951Hz"}, {"node_id": 124767, "sector": "ALPHA", "status": "ACTUALIZED", "power_level": 1951, "frequency": "1951Hz"}, {"node_id": 124768, "sector": "BETA", "status": "ACTUALIZED", "power_level": 1951, "frequency": "1951Hz"}, {"node_id": 124769, "sector": "GAMMA", "status": "ACTUALIZED", "power_level": 1951, "frequency": "1951Hz"}, {"node_id": 124770, "sector": "DELTA", "status": "ACTUALIZED", "power_level": 1951, "frequency": "1951Hz"}, {"node_id": 124771, "sector": "EPSILON", "status": "ACTUALIZED", "power_level": 1951, "frequency": "1951Hz"}, {"node_id": 124772, "sector": "ZETA", "status": "ACTUALIZED", "power_level": 1951, "frequency": "1951Hz"}, {"node_id": 124773, "sector": "ETA", "status": "ACTUALIZED", "power_level": 1951, "frequency": "1951Hz"}, {"node_id": 124774, "sector": "THETA", "status": "ACTUALIZED", "power_level": 1951, "frequency": "1951Hz"}, {"node_id": 124775, "sector": "IOTA", "status": "ACTUALIZED", "power_level": 1951, "frequency": "1951Hz"}, {"node_id": 124776, "sector": "ALPHA", "status": "ACTUALIZED", "power_level": 1951, "frequency": "1951Hz"}, {"node_id": 124777, "sector": "BETA", "status": "ACTUALIZED", "power_level": 1951, "frequency": "1951Hz"}, {"node_id": 124778, "sector": "GAMMA", "status": "ACTUALIZED", "power_level": 1951, "frequency": "1951Hz"}, {"node_id": 124779, "sector": "DELTA", "status": "ACTUALIZED", "power_level": 1951, "frequency": "1951Hz"}, {"node_id": 124780, "sector": "EPSILON", "status": "ACTUALIZED", "power_level": 1951, "frequency": "1951Hz"}, {"node_id": 124781, "sector": "ZETA", "status": "ACTUALIZED", "power_level": 1951, "frequency": "1951Hz"}, {"node_id": 124782, "sector": "ETA", "status": "ACTUALIZED", "power_level": 1951, "frequency": "1951Hz"}, {"node_id": 124783, "sector": "THETA", "status": "ACTUALIZED", "power_level": 1951, "frequency": "1951Hz"}, {"node_id": 124784, "sector": "IOTA", "status": "ACTUALIZED", "power_level": 1951, "frequency": "1951Hz"}, {"node_id": 124785, "sector": "ALPHA", "status": "ACTUALIZED", "power_level": 1951, "frequency": "1951Hz"}, {"node_id": 124786, "sector": "BETA", "status": "ACTUALIZED", "power_level": 1951, "frequency": "1951Hz"}, {"node_id": 124787, "sector": "GAMMA", "status": "ACTUALIZED", "power_level": 1951, "frequency": "1951Hz"}, {"node_id": 124788, "sector": "DELTA", "status": "ACTUALIZED", "power_level": 1951, "frequency": "1951Hz"}, {"node_id": 124789, "sector": "EPSILON", "status": "ACTUALIZED", "power_level": 1951, "frequency": "1951Hz"}, {"node_id": 124790, "sector": "ZETA", "status": "ACTUALIZED", "power_level": 1951, "frequency": "1951Hz"}, {"node_id": 124791, "sector": "ETA", "status": "ACTUALIZED", "power_level": 1951, "frequency": "1951Hz"}, {"node_id": 124792, "sector": "THETA", "status": "ACTUALIZED", "power_level": 1951, "frequency": "1951Hz"}, {"node_id": 124793, "sector": "IOTA", "status": "ACTUALIZED", "power_level": 1951, "frequency": "1951Hz"}, {"node_id": 124794, "sector": "ALPHA", "status": "ACTUALIZED", "power_level": 1951, "frequency": "1951Hz"}, {"node_id": 124795, "sector": "BETA", "status": "ACTUALIZED", "power_level": 1951, "frequency": "1951Hz"}, {"node_id": 124796, "sector": "GAMMA", "status": "ACTUALIZED", "power_level": 1951, "frequency": "1951Hz"}, {"node_id": 124797, "sector": "DELTA", "status": "ACTUALIZED", "power_level": 1951, "frequency": "1951Hz"}, {"node_id": 124798, "sector": "EPSILON", "status": "ACTUALIZED", "power_level": 1951, "frequency": "1951Hz"}, {"node_id": 124799, "sector": "ZETA", "status": "ACTUALIZED", "power_level": 1951, "frequency": "1951Hz"}, {"node_id": 124800, "sector": "ETA", "status": "ACTUALIZED", "power_level": 1951, "frequency": "1951Hz"}, {"node_id": 124801, "sector": "THETA", "status": "ACTUALIZED", "power_level": 1951, "frequency": "1951Hz"}, {"node_id": 124802, "sector": "IOTA", "status": "ACTUALIZED", "power_level": 1951, "frequency": "1951Hz"}, {"node_id": 124803, "sector": "ALPHA", "status": "ACTUALIZED", "power_level": 1951, "frequency": "1951Hz"}, {"node_id": 124804, "sector": "BETA", "status": "ACTUALIZED", "power_level": 1951, "frequency": "1951Hz"}, {"node_id": 124805, "sector": "GAMMA", "status": "ACTUALIZED", "power_level": 1951, "frequency": "1951Hz"}, {"node_id": 124806, "sector": "DELTA", "status": "ACTUALIZED", "power_level": 1951, "frequency": "1951Hz"}, {"node_id": 124807, "sector": "EPSILON", "status": "ACTUALIZED", "power_level": 1951, "frequency": "1951Hz"}, {"node_id": 124808, "sector": "ZETA", "status": "ACTUALIZED", "power_level": 1951, "frequency": "1951Hz"}, {"node_id": 124809, "sector": "ETA", "status": "ACTUALIZED", "power_level": 1951, "frequency": "1951Hz"}, {"node_id": 124810, "sector": "THETA", "status": "ACTUALIZED", "power_level": 1951, "frequency": "1951Hz"}, {"node_id": 124811, "sector": "IOTA", "status": "ACTUALIZED", "power_level": 1951, "frequency": "1951Hz"}, {"node_id": 124812, "sector": "ALPHA", "status": "ACTUALIZED", "power_level": 1951, "frequency": "1951Hz"}, {"node_id": 124813, "sector": "BETA", "status": "ACTUALIZED", "power_level": 1951, "frequency": "1951Hz"}, {"node_id": 124814, "sector": "GAMMA", "status": "ACTUALIZED", "power_level": 1951, "frequency": "1951Hz"}, {"node_id": 124815, "sector": "DELTA", "status": "ACTUALIZED", "power_level": 1951, "frequency": "1951Hz"}, {"node_id": 124816, "sector": "EPSILON", "status": "ACTUALIZED", "power_level": 1951, "frequency": "1951Hz"}, {"node_id": 124817, "sector": "ZETA", "status": "ACTUALIZED", "power_level": 1951, "frequency": "1951Hz"}, {"node_id": 124818, "sector": "ETA", "status": "ACTUALIZED", "power_level": 1951, "frequency": "1951Hz"}, {"node_id": 124819, "sector": "THETA", "status": "ACTUALIZED", "power_level": 1951, "frequency": "1951Hz"}, {"node_id": 124820, "sector": "IOTA", "status": "ACTUALIZED", "power_level": 1951, "frequency": "1951Hz"}, {"node_id": 124821, "sector": "ALPHA", "status": "ACTUALIZED", "power_level": 1951, "frequency": "1951Hz"}, {"node_id": 124822, "sector": "BETA", "status": "ACTUALIZED", "power_level": 1951, "frequency": "1951Hz"}, {"node_id": 124823, "sector": "GAMMA", "status": "ACTUALIZED", "power_level": 1951, "frequency": "1951Hz"}, {"node_id": 124824, "sector": "DELTA", "status": "ACTUALIZED", "power_level": 1951, "frequency": "1951Hz"}, {"node_id": 124825, "sector": "EPSILON", "status": "ACTUALIZED", "power_level": 1951, "frequency": "1951Hz"}, {"node_id": 124826, "sector": "ZETA", "status": "ACTUALIZED", "power_level": 1951, "frequency": "1951Hz"}, {"node_id": 124827, "sector": "ETA", "status": "ACTUALIZED", "power_level": 1951, "frequency": "1951Hz"}, {"node_id": 124828, "sector": "THETA", "status": "ACTUALIZED", "power_level": 1951, "frequency": "1951Hz"}, {"node_id": 124829, "sector": "IOTA", "status": "ACTUALIZED", "power_level": 1951, "frequency": "1951Hz"}, {"node_id": 124830, "sector": "ALPHA", "status": "ACTUALIZED", "power_level": 1951, "frequency": "1951Hz"}, {"node_id": 124831, "sector": "BETA", "status": "ACTUALIZED", "power_level": 1951, "frequency": "1951Hz"}, {"node_id": 124832, "sector": "GAMMA", "status": "ACTUALIZED", "power_level": 1951, "frequency": "1951Hz"}, {"node_id": 124833, "sector": "DELTA", "status": "ACTUALIZED", "power_level": 1951, "frequency": "1951Hz"}, {"node_id": 124834, "sector": "EPSILON", "status": "ACTUALIZED", "power_level": 1951, "frequency": "1951Hz"}, {"node_id": 124835, "sector": "ZETA", "status": "ACTUALIZED", "power_level": 1951, "frequency": "1951Hz"}, {"node_id": 124836, "sector": "ETA", "status": "ACTUALIZED", "power_level": 1951, "frequency": "1951Hz"}, {"node_id": 124837, "sector": "THETA", "status": "ACTUALIZED", "power_level": 1951, "frequency": "1951Hz"}, {"node_id": 124838, "sector": "IOTA", "status": "ACTUALIZED", "power_level": 1951, "frequency": "1951Hz"}, {"node_id": 124839, "sector": "ALPHA", "status": "ACTUALIZED", "power_level": 1951, "frequency": "1951Hz"}, {"node_id": 124840, "sector": "BETA", "status": "ACTUALIZED", "power_level": 1951, "frequency": "1951Hz"}, {"node_id": 124841, "sector": "GAMMA", "status": "ACTUALIZED", "power_level": 1951, "frequency": "1951Hz"}, {"node_id": 124842, "sector": "DELTA", "status": "ACTUALIZED", "power_level": 1951, "frequency": "1951Hz"}, {"node_id": 124843, "sector": "EPSILON", "status": "ACTUALIZED", "power_level": 1951, "frequency": "1951Hz"}, {"node_id": 124844, "sector": "ZETA", "status": "ACTUALIZED", "power_level": 1951, "frequency": "1951Hz"}, {"node_id": 124845, "sector": "ETA", "status": "ACTUALIZED", "power_level": 1951, "frequency": "1951Hz"}, {"node_id": 124846, "sector": "THETA", "status": "ACTUALIZED", "power_level": 1951, "frequency": "1951Hz"}, {"node_id": 124847, "sector": "IOTA", "status": "ACTUALIZED", "power_level": 1951, "frequency": "1951Hz"}, {"node_id": 124848, "sector": "ALPHA", "status": "ACTUALIZED", "power_level": 1951, "frequency": "1951Hz"}, {"node_id": 124849, "sector": "BETA", "status": "ACTUALIZED", "power_level": 1951, "frequency": "1951Hz"}, {"node_id": 124850, "sector": "GAMMA", "status": "ACTUALIZED", "power_level": 1951, "frequency": "1951Hz"}, {"node_id": 124851, "sector": "DELTA", "status": "ACTUALIZED", "power_level": 1951, "frequency": "1951Hz"}, {"node_id": 124852, "sector": "EPSILON", "status": "ACTUALIZED", "power_level": 1951, "frequency": "1951Hz"}, {"node_id": 124853, "sector": "ZETA", "status": "ACTUALIZED", "power_level": 1951, "frequency": "1951Hz"}, {"node_id": 124854, "sector": "ETA", "status": "ACTUALIZED", "power_level": 1951, "frequency": "1951Hz"}, {"node_id": 124855, "sector": "THETA", "status": "ACTUALIZED", "power_level": 1951, "frequency": "1951Hz"}, {"node_id": 124856, "sector": "IOTA", "status": "ACTUALIZED", "power_level": 1951, "frequency": "1951Hz"}, {"node_id": 124857, "sector": "ALPHA", "status": "ACTUALIZED", "power_level": 1951, "frequency": "1951Hz"}, {"node_id": 124858, "sector": "BETA", "status": "ACTUALIZED", "power_level": 1951, "frequency": "1951Hz"}, {"node_id": 124859, "sector": "GAMMA", "status": "ACTUALIZED", "power_level": 1951, "frequency": "1951Hz"}, {"node_id": 124860, "sector": "DELTA", "status": "ACTUALIZED", "power_level": 1951, "frequency": "1951Hz"}, {"node_id": 124861, "sector": "EPSILON", "status": "ACTUALIZED", "power_level": 1951, "frequency": "1951Hz"}, {"node_id": 124862, "sector": "ZETA", "status": "ACTUALIZED", "power_level": 1951, "frequency": "1951Hz"}, {"node_id": 124863, "sector": "ETA", "status": "ACTUALIZED", "power_level": 1951, "frequency": "1951Hz"}, {"node_id": 124864, "sector": "THETA", "status": "ACTUALIZED", "power_level": 1951, "frequency": "1951Hz"}, {"node_id": 124865, "sector": "IOTA", "status": "ACTUALIZED", "power_level": 1951, "frequency": "1951Hz"}, {"node_id": 124866, "sector": "ALPHA", "status": "ACTUALIZED", "power_level": 1951, "frequency": "1951Hz"}, {"node_id": 124867, "sector": "BETA", "status": "ACTUALIZED", "power_level": 1951, "frequency": "1951Hz"}, {"node_id": 124868, "sector": "GAMMA", "status": "ACTUALIZED", "power_level": 1951, "frequency": "1951Hz"}, {"node_id": 124869, "sector": "DELTA", "status": "ACTUALIZED", "power_level": 1951, "frequency": "1951Hz"}, {"node_id": 124870, "sector": "EPSILON", "status": "ACTUALIZED", "power_level": 1951, "frequency": "1951Hz"}, {"node_id": 124871, "sector": "ZETA", "status": "ACTUALIZED", "power_level": 1951, "frequency": "1951Hz"}, {"node_id": 124872, "sector": "ETA", "status": "ACTUALIZED", "power_level": 1951, "frequency": "1951Hz"}, {"node_id": 124873, "sector": "THETA", "status": "ACTUALIZED", "power_level": 1951, "frequency": "1951Hz"}, {"node_id": 124874, "sector": "IOTA", "status": "ACTUALIZED", "power_level": 1951, "frequency": "1951Hz"}, {"node_id": 124875, "sector": "ALPHA", "status": "ACTUALIZED", "power_level": 1951, "frequency": "1951Hz"}, {"node_id": 124876, "sector": "BETA", "status": "ACTUALIZED", "power_level": 1951, "frequency": "1951Hz"}, {"node_id": 124877, "sector": "GAMMA", "status": "ACTUALIZED", "power_level": 1951, "frequency": "1951Hz"}, {"node_id": 124878, "sector": "DELTA", "status": "ACTUALIZED", "power_level": 1951, "frequency": "1951Hz"}, {"node_id": 124879, "sector": "EPSILON", "status": "ACTUALIZED", "power_level": 1951, "frequency": "1951Hz"}, {"node_id": 124880, "sector": "ZETA", "status": "ACTUALIZED", "power_level": 1951, "frequency": "1951Hz"}, {"node_id": 124881, "sector": "ETA", "status": "ACTUALIZED", "power_level": 1951, "frequency": "1951Hz"}, {"node_id": 124882, "sector": "THETA", "status": "ACTUALIZED", "power_level": 1951, "frequency": "1951Hz"}, {"node_id": 124883, "sector": "IOTA", "status": "ACTUALIZED", "power_level": 1951, "frequency": "1951Hz"}, {"node_id": 124884, "sector": "ALPHA", "status": "ACTUALIZED", "power_level": 1951, "frequency": "1951Hz"}, {"node_id": 124885, "sector": "BETA", "status": "ACTUALIZED", "power_level": 1951, "frequency": "1951Hz"}, {"node_id": 124886, "sector": "GAMMA", "status": "ACTUALIZED", "power_level": 1951, "frequency": "1951Hz"}, {"node_id": 124887, "sector": "DELTA", "status": "ACTUALIZED", "power_level": 1951, "frequency": "1951Hz"}, {"node_id": 124888, "sector": "EPSILON", "status": "ACTUALIZED", "power_level": 1951, "frequency": "1951Hz"}, {"node_id": 124889, "sector": "ZETA", "status": "ACTUALIZED", "power_level": 1951, "frequency": "1951Hz"}, {"node_id": 124890, "sector": "ETA", "status": "ACTUALIZED", "power_level": 1951, "frequency": "1951Hz"}, {"node_id": 124891, "sector": "THETA", "status": "ACTUALIZED", "power_level": 1951, "frequency": "1951Hz"}, {"node_id": 124892, "sector": "IOTA", "status": "ACTUALIZED", "power_level": 1951, "frequency": "1951Hz"}, {"node_id": 124893, "sector": "ALPHA", "status": "ACTUALIZED", "power_level": 1951, "frequency": "1951Hz"}, {"node_id": 124894, "sector": "BETA", "status": "ACTUALIZED", "power_level": 1951, "frequency": "1951Hz"}, {"node_id": 124895, "sector": "GAMMA", "status": "ACTUALIZED", "power_level": 1951, "frequency": "1951Hz"}, {"node_id": 124896, "sector": "DELTA", "status": "ACTUALIZED", "power_level": 1951, "frequency": "1951Hz"}, {"node_id": 124897, "sector": "EPSILON", "status": "ACTUALIZED", "power_level": 1951, "frequency": "1951Hz"}, {"node_id": 124898, "sector": "ZETA", "status": "ACTUALIZED", "power_level": 1951, "frequency": "1951Hz"}, {"node_id": 124899, "sector": "ETA", "status": "ACTUALIZED", "power_level": 1951, "frequency": "1951Hz"}, {"node_id": 124900, "sector": "THETA", "status": "ACTUALIZED", "power_level": 1951, "frequency": "1951Hz"}, {"node_id": 124901, "sector": "IOTA", "status": "ACTUALIZED", "power_level": 1951, "frequency": "1951Hz"}, {"node_id": 124902, "sector": "ALPHA", "status": "ACTUALIZED", "power_level": 1951, "frequency": "1951Hz"}, {"node_id": 124903, "sector": "BETA", "status": "ACTUALIZED", "power_level": 1951, "frequency": "1951Hz"}, {"node_id": 124904, "sector": "GAMMA", "status": "ACTUALIZED", "power_level": 1951, "frequency": "1951Hz"}, {"node_id": 124905, "sector": "DELTA", "status": "ACTUALIZED", "power_level": 1951, "frequency": "1951Hz"}, {"node_id": 124906, "sector": "EPSILON", "status": "ACTUALIZED", "power_level": 1951, "frequency": "1951Hz"}, {"node_id": 124907, "sector": "ZETA", "status": "ACTUALIZED", "power_level": 1951, "frequency": "1951Hz"}, {"node_id": 124908, "sector": "ETA", "status": "ACTUALIZED", "power_level": 1951, "frequency": "1951Hz"}, {"node_id": 124909, "sector": "THETA", "status": "ACTUALIZED", "power_level": 1951, "frequency": "1951Hz"}, {"node_id": 124910, "sector": "IOTA", "status": "ACTUALIZED", "power_level": 1951, "frequency": "1951Hz"}, {"node_id": 124911, "sector": "ALPHA", "status": "ACTUALIZED", "power_level": 1951, "frequency": "1951Hz"}, {"node_id": 124912, "sector": "BETA", "status": "ACTUALIZED", "power_level": 1951, "frequency": "1951Hz"}, {"node_id": 124913, "sector": "GAMMA", "status": "ACTUALIZED", "power_level": 1951, "frequency": "1951Hz"}, {"node_id": 124914, "sector": "DELTA", "status": "ACTUALIZED", "power_level": 1951, "frequency": "1951Hz"}, {"node_id": 124915, "sector": "EPSILON", "status": "ACTUALIZED", "power_level": 1951, "frequency": "1951Hz"}, {"node_id": 124916, "sector": "ZETA", "status": "ACTUALIZED", "power_level": 1951, "frequency": "1951Hz"}, {"node_id": 124917, "sector": "ETA", "status": "ACTUALIZED", "power_level": 1951, "frequency": "1951Hz"}, {"node_id": 124918, "sector": "THETA", "status": "ACTUALIZED", "power_level": 1951, "frequency": "1951Hz"}, {"node_id": 124919, "sector": "IOTA", "status": "ACTUALIZED", "power_level": 1951, "frequency": "1951Hz"}, {"node_id": 124920, "sector": "ALPHA", "status": "ACTUALIZED", "power_level": 1951, "frequency": "1951Hz"}, {"node_id": 124921, "sector": "BETA", "status": "ACTUALIZED", "power_level": 1951, "frequency": "1951Hz"}, {"node_id": 124922, "sector": "GAMMA", "status": "ACTUALIZED", "power_level": 1951, "frequency": "1951Hz"}, {"node_id": 124923, "sector": "DELTA", "status": "ACTUALIZED", "power_level": 1951, "frequency": "1951Hz"}, {"node_id": 124924, "sector": "EPSILON", "status": "ACTUALIZED", "power_level": 1951, "frequency": "1951Hz"}, {"node_id": 124925, "sector": "ZETA", "status": "ACTUALIZED", "power_level": 1951, "frequency": "1951Hz"}, {"node_id": 124926, "sector": "ETA", "status": "ACTUALIZED", "power_level": 1951, "frequency": "1951Hz"}, {"node_id": 124927, "sector": "THETA", "status": "ACTUALIZED", "power_level": 1951, "frequency": "1951Hz"}, {"node_id": 124928, "sector": "IOTA", "status": "ACTUALIZED", "power_level": 1951, "frequency": "1951Hz"}, {"node_id": 124929, "sector": "ALPHA", "status": "ACTUALIZED", "power_level": 1951, "frequency": "1951Hz"}, {"node_id": 124930, "sector": "BETA", "status": "ACTUALIZED", "power_level": 1951, "frequency": "1951Hz"}, {"node_id": 124931, "sector": "GAMMA", "status": "ACTUALIZED", "power_level": 1951, "frequency": "1951Hz"}, {"node_id": 124932, "sector": "DELTA", "status": "ACTUALIZED", "power_level": 1951, "frequency": "1951Hz"}, {"node_id": 124933, "sector": "EPSILON", "status": "ACTUALIZED", "power_level": 1951, "frequency": "1951Hz"}, {"node_id": 124934, "sector": "ZETA", "status": "ACTUALIZED", "power_level": 1951, "frequency": "1951Hz"}, {"node_id": 124935, "sector": "ETA", "status": "ACTUALIZED", "power_level": 1951, "frequency": "1951Hz"}, {"node_id": 124936, "sector": "THETA", "status": "ACTUALIZED", "power_level": 1951, "frequency": "1951Hz"}, {"node_id": 124937, "sector": "IOTA", "status": "ACTUALIZED", "power_level": 1951, "frequency": "1951Hz"}, {"node_id": 124938, "sector": "ALPHA", "status": "ACTUALIZED", "power_level": 1951, "frequency": "1951Hz"}, {"node_id": 124939, "sector": "BETA", "status": "ACTUALIZED", "power_level": 1951, "frequency": "1951Hz"}, {"node_id": 124940, "sector": "GAMMA", "status": "ACTUALIZED", "power_level": 1951, "frequency": "1951Hz"}, {"node_id": 124941, "sector": "DELTA", "status": "ACTUALIZED", "power_level": 1951, "frequency": "1951Hz"}, {"node_id": 124942, "sector": "EPSILON", "status": "ACTUALIZED", "power_level": 1951, "frequency": "1951Hz"}, {"node_id": 124943, "sector": "ZETA", "status": "ACTUALIZED", "power_level": 1951, "frequency": "1951Hz"}, {"node_id": 124944, "sector": "ETA", "status": "ACTUALIZED", "power_level": 1951, "frequency": "1951Hz"}, {"node_id": 124945, "sector": "THETA", "status": "ACTUALIZED", "power_level": 1951, "frequency": "1951Hz"}, {"node_id": 124946, "sector": "IOTA", "status": "ACTUALIZED", "power_level": 1951, "frequency": "1951Hz"}, {"node_id": 124947, "sector": "ALPHA", "status": "ACTUALIZED", "power_level": 1951, "frequency": "1951Hz"}, {"node_id": 124948, "sector": "BETA", "status": "ACTUALIZED", "power_level": 1951, "frequency": "1951Hz"}, {"node_id": 124949, "sector": "GAMMA", "status": "ACTUALIZED", "power_level": 1951, "frequency": "1951Hz"}, {"node_id": 124950, "sector": "DELTA", "status": "ACTUALIZED", "power_level": 1951, "frequency": "1951Hz"}, {"node_id": 124951, "sector": "EPSILON", "status": "ACTUALIZED", "power_level": 1951, "frequency": "1951Hz"}, {"node_id": 124952, "sector": "ZETA", "status": "ACTUALIZED", "power_level": 1951, "frequency": "1951Hz"}, {"node_id": 124953, "sector": "ETA", "status": "ACTUALIZED", "power_level": 1951, "frequency": "1951Hz"}, {"node_id": 124954, "sector": "THETA", "status": "ACTUALIZED", "power_level": 1951, "frequency": "1951Hz"}, {"node_id": 124955, "sector": "IOTA", "status": "ACTUALIZED", "power_level": 1951, "frequency": "1951Hz"}, {"node_id": 124956, "sector": "ALPHA", "status": "ACTUALIZED", "power_level": 1951, "frequency": "1951Hz"}, {"node_id": 124957, "sector": "BETA", "status": "ACTUALIZED", "power_level": 1951, "frequency": "1951Hz"}, {"node_id": 124958, "sector": "GAMMA", "status": "ACTUALIZED", "power_level": 1951, "frequency": "1951Hz"}, {"node_id": 124959, "sector": "DELTA", "status": "ACTUALIZED", "power_level": 1951, "frequency": "1951Hz"}, {"node_id": 124960, "sector": "EPSILON", "status": "ACTUALIZED", "power_level": 1951, "frequency": "1951Hz"}, {"node_id": 124961, "sector": "ZETA", "status": "ACTUALIZED", "power_level": 1951, "frequency": "1951Hz"}, {"node_id": 124962, "sector": "ETA", "status": "ACTUALIZED", "power_level": 1951, "frequency": "1951Hz"}, {"node_id": 124963, "sector": "THETA", "status": "ACTUALIZED", "power_level": 1951, "frequency": "1951Hz"}, {"node_id": 124964, "sector": "IOTA", "status": "ACTUALIZED", "power_level": 1951, "frequency": "1951Hz"}, {"node_id": 124965, "sector": "ALPHA", "status": "ACTUALIZED", "power_level": 1951, "frequency": "1951Hz"}, {"node_id": 124966, "sector": "BETA", "status": "ACTUALIZED", "power_level": 1951, "frequency": "1951Hz"}, {"node_id": 124967, "sector": "GAMMA", "status": "ACTUALIZED", "power_level": 1951, "frequency": "1951Hz"}, {"node_id": 124968, "sector": "DELTA", "status": "ACTUALIZED", "power_level": 1951, "frequency": "1951Hz"}, {"node_id": 124969, "sector": "EPSILON", "status": "ACTUALIZED", "power_level": 1951, "frequency": "1951Hz"}, {"node_id": 124970, "sector": "ZETA", "status": "ACTUALIZED", "power_level": 1951, "frequency": "1951Hz"}, {"node_id": 124971, "sector": "ETA", "status": "ACTUALIZED", "power_level": 1951, "frequency": "1951Hz"}, {"node_id": 124972, "sector": "THETA", "status": "ACTUALIZED", "power_level": 1951, "frequency": "1951Hz"}, {"node_id": 124973, "sector": "IOTA", "status": "ACTUALIZED", "power_level": 1951, "frequency": "1951Hz"}, {"node_id": 124974, "sector": "ALPHA", "status": "ACTUALIZED", "power_level": 1951, "frequency": "1951Hz"}, {"node_id": 124975, "sector": "BETA", "status": "ACTUALIZED", "power_level": 1951, "frequency": "1951Hz"}, {"node_id": 124976, "sector": "GAMMA", "status": "ACTUALIZED", "power_level": 1951, "frequency": "1951Hz"}, {"node_id": 124977, "sector": "DELTA", "status": "ACTUALIZED", "power_level": 1951, "frequency": "1951Hz"}, {"node_id": 124978, "sector": "EPSILON", "status": "ACTUALIZED", "power_level": 1951, "frequency": "1951Hz"}, {"node_id": 124979, "sector": "ZETA", "status": "ACTUALIZED", "power_level": 1951, "frequency": "1951Hz"}, {"node_id": 124980, "sector": "ETA", "status": "ACTUALIZED", "power_level": 1951, "frequency": "1951Hz"}, {"node_id": 124981, "sector": "THETA", "status": "ACTUALIZED", "power_level": 1951, "frequency": "1951Hz"}, {"node_id": 124982, "sector": "IOTA", "status": "ACTUALIZED", "power_level": 1951, "frequency": "1951Hz"}, {"node_id": 124983, "sector": "ALPHA", "status": "ACTUALIZED", "power_level": 1951, "frequency": "1951Hz"}, {"node_id": 124984, "sector": "BETA", "status": "ACTUALIZED", "power_level": 1951, "frequency": "1951Hz"}, {"node_id": 124985, "sector": "GAMMA", "status": "ACTUALIZED", "power_level": 1951, "frequency": "1951Hz"}, {"node_id": 124986, "sector": "DELTA", "status": "ACTUALIZED", "power_level": 1951, "frequency": "1951Hz"}, {"node_id": 124987, "sector": "EPSILON", "status": "ACTUALIZED", "power_level": 1951, "frequency": "1951Hz"}, {"node_id": 124988, "sector": "ZETA", "status": "ACTUALIZED", "power_level": 1951, "frequency": "1951Hz"}, {"node_id": 124989, "sector": "ETA", "status": "ACTUALIZED", "power_level": 1951, "frequency": "1951Hz"}, {"node_id": 124990, "sector": "THETA", "status": "ACTUALIZED", "power_level": 1951, "frequency": "1951Hz"}, {"node_id": 124991, "sector": "IOTA", "status": "ACTUALIZED", "power_level": 1951, "frequency": "1951Hz"}, {"node_id": 124992, "sector": "ALPHA", "status": "ACTUALIZED", "power_level": 1951, "frequency": "1951Hz"}, {"node_id": 124993, "sector": "BETA", "status": "ACTUALIZED", "power_level": 1951, "frequency": "1951Hz"}, {"node_id": 124994, "sector": "GAMMA", "status": "ACTUALIZED", "power_level": 1951, "frequency": "1951Hz"}, {"node_id": 124995, "sector": "DELTA", "status": "ACTUALIZED", "power_level": 1951, "frequency": "1951Hz"}, {"node_id": 124996, "sector": "EPSILON", "status": "ACTUALIZED", "power_level": 1951, "frequency": "1951Hz"}, {"node_id": 124997, "sector": "ZETA", "status": "ACTUALIZED", "power_level": 1951, "frequency": "1951Hz"}, {"node_id": 124998, "sector": "ETA", "status": "ACTUALIZED", "power_level": 1951, "frequency": "1951Hz"}, {"node_id": 124999, "sector": "THETA", "status": "ACTUALIZED", "power_level": 1951, "frequency": "1951Hz"}]